aio_msgpack_rpc/__init__.py
aio_msgpack_rpc/client.py
aio_msgpack_rpc/error.py
aio_msgpack_rpc/request.py
aio_msgpack_rpc/server.py
aio_msgpack_rpc-0.1.0.dist-info/METADATA
aio_msgpack_rpc-0.1.0.dist-info/RECORD
aio_msgpack_rpc-0.1.0.dist-info/WHEEL
aio_msgpack_rpc-0.1.0.dist-info/top_level.txt
