Metadata-Version: 2.1
Name: aio-msgpack-rpc
Version: 0.1.0
Summary: asyncio MsgPack RPC
Home-page: https://gitlab.com/rmcgregor/aio-msgpack-rpc
Author: Robert Mcgregor
Author-email: rmcgregor1990@gmail.com
License: UNKNOWN
Platform: UNKNOWN
Classifier: Development Status :: 3 - Alpha
Classifier: Framework :: AsyncIO
Classifier: License :: OSI Approved :: MIT License
Classifier: Programming Language :: Python :: 3.6
Classifier: Operating System :: OS Independent
Requires-Python: >=3.6
Provides-Extra: test
Requires-Dist: msgpack
Provides-Extra: test
Requires-Dist: pytest; extra == 'test'
Requires-Dist: pytest-asyncio; extra == 'test'
Requires-Dist: asyncio-extras; extra == 'test'
